genx_ai_camera_panel/__init__.py
genx_ai_camera_panel/api.cpython-310-x86_64-linux-gnu.so
genx_ai_camera_panel/app.cpython-310-x86_64-linux-gnu.so
genx_ai_camera_panel/config.cpython-310-x86_64-linux-gnu.so
genx_ai_camera_panel/constants.cpython-310-x86_64-linux-gnu.so
genx_ai_camera_panel/db.cpython-310-x86_64-linux-gnu.so
genx_ai_camera_panel/ffmpeg_helper.cpython-310-x86_64-linux-gnu.so
genx_ai_camera_panel/guid.cpython-310-x86_64-linux-gnu.so
genx_ai_camera_panel/main.cpython-310-x86_64-linux-gnu.so
genx_ai_camera_panel/mdns.cpython-310-x86_64-linux-gnu.so
genx_ai_camera_panel/mkcert.cpython-310-x86_64-linux-gnu.so
genx_ai_camera_panel/net_helper.cpython-310-x86_64-linux-gnu.so
genx_ai_camera_panel/onvif_wrapper.cpython-310-x86_64-linux-gnu.so
genx_ai_camera_panel/onvif_wrapper.py
genx_ai_camera_panel/player.cpython-310-x86_64-linux-gnu.so
genx_ai_camera_panel/server.cpython-310-x86_64-linux-gnu.so
genx_ai_camera_panel/setup.cpython-310-x86_64-linux-gnu.so
genx_ai_camera_panel/tunnel_helper.cpython-310-x86_64-linux-gnu.so
genx_ai_camera_panel/resources/templates/index.html
genx_ai_camera_panel/resources/templates/login.html
genx_ai_camera_panel/resources/templates/manual.html
genx_ai_camera_panel/resources/templates/no_internet.html
genx_ai_camera_panel/resources/templates/player.html
genx_ai_camera_panel/resources/templates/success.html
genx_ai_camera_panel/resources/templates/wifi_config.html
genx_ai_camera_panel/scripts/cleanup_hosts.bat
genx_ai_camera_panel/scripts/cleanup_hosts.sh
genx_ai_camera_panel/scripts/hosts.bat
genx_ai_camera_panel/scripts/hosts.sh
genx_ai_camera_panel/service/genx-ai-camera-panel.plist
genx_ai_camera_panel/service/genx-ai-camera-panel.service
genx_ai_camera_panel/service/windows_service.cpython-310-x86_64-linux-gnu.so
genx_ai_camera_panel/static/css/bootstrap-icons.min.css
genx_ai_camera_panel/static/css/bootstrap.min.css
genx_ai_camera_panel/static/css/dataTables.bootstrap5.css
genx_ai_camera_panel-2.2.0.dist-info/METADATA
genx_ai_camera_panel-2.2.0.dist-info/WHEEL
genx_ai_camera_panel-2.2.0.dist-info/entry_points.txt
genx_ai_camera_panel-2.2.0.dist-info/top_level.txt
genx_ai_camera_panel-2.2.0.dist-info/RECORD
