Metadata-Version: 2.4
Name: genx-ai-camera-panel
Version: 2.2.0
Summary: Camera management for GenX AI
Author-email: Jaydeep Ukani <jaydeepukani@outlook.in>
Project-URL: Homepage, https://github.com/jaydeepukani/GenX-AI-Cameras-Managment
Project-URL: Issues, https://github.com/jaydeepukani/GenX-AI-Cameras-Managment/issues
Classifier: Programming Language :: Python :: 3
Classifier: Operating System :: OS Independent
Requires-Python: >=3.10
Requires-Dist: art>=6.2
Requires-Dist: flask>=3.0.3
Requires-Dist: psutil>=5.9.8
Requires-Dist: requests>=2.32.2
Requires-Dist: WSDiscovery>=2.0.0
Requires-Dist: XlsxWriter>=3.2.0
Requires-Dist: zeep>=4.2.1
Requires-Dist: zeroconf>=0.146.1
Requires-Dist: flask-cors>=5.0.1
Requires-Dist: gunicorn>=23.0.0
Requires-Dist: gevent>=24.11.1
Requires-Dist: opencv-python-headless>=4.10.0.84
Requires-Dist: wifi>=0.3.8
Requires-Dist: websockets>=15.0.1
Requires-Dist: setproctitle>=1.3.5
